{
    "_links": {
        "self": {
            "href": ""
        },
        "type": {
            "href": "http:\/\/drupal.org\/rest\/type\/paragraph\/rich_text"
        }
    },
    "id": [
        {
            "value": 318
        }
    ],
    "uuid": [
        {
            "value": "5521a348-e051-46d7-a93f-9fa0ef085783"
        }
    ],
    "revision_id": [
        {
            "value": 984
        }
    ],
    "langcode": [
        {
            "value": "en",
            "lang": "en"
        }
    ],
    "type": [
        {
            "target_id": "rich_text"
        }
    ],
    "status": [
        {
            "value": true,
            "lang": "en"
        }
    ],
    "created": [
        {
            "value": "2019-10-17T20:15:54+00:00",
            "lang": "en",
            "format": "Y-m-d\\TH:i:sP"
        }
    ],
    "parent_id": [
        {
            "value": "273"
        }
    ],
    "parent_type": [
        {
            "value": "paragraph"
        }
    ],
    "parent_field_name": [
        {
            "value": "field_components"
        }
    ],
    "behavior_settings": [
        {
            "value": []
        }
    ],
    "default_langcode": [
        {
            "value": true,
            "lang": "en"
        }
    ],
    "field_text": [
        {
            "value": "<p>And here's a link rendered as a button in a theme color:<\/p>\r\n",
            "format": "filtered_html",
            "processed": "<p>And here's a link rendered as a button in a theme color:<\/p>",
            "lang": "en"
        }
    ]
}